pytest_localserver/__init__.py
pytest_localserver/_version.py
pytest_localserver/cert.crt
pytest_localserver/http.py
pytest_localserver/https.py
pytest_localserver/plugin.py
pytest_localserver/server.key
pytest_localserver/smtp.py
pytest_localserver-0.9.0.dist-info/AUTHORS
pytest_localserver-0.9.0.dist-info/LICENSE
pytest_localserver-0.9.0.dist-info/METADATA
pytest_localserver-0.9.0.dist-info/WHEEL
pytest_localserver-0.9.0.dist-info/entry_points.txt
pytest_localserver-0.9.0.dist-info/top_level.txt
pytest_localserver-0.9.0.dist-info/RECORD
