Metadata-Version: 2.1
Name: pytest-localserver
Version: 0.9.0
Summary: pytest plugin to test server connections locally.
Home-page: https://github.com/pytest-dev/pytest-localserver
Author: Sebastian Rahlf
Author-email: basti@redtoad.de
Maintainer: David Zaslavsky
Maintainer-email: diazona@ellipsix.net
License: MIT License
Keywords: pytest server localhost http smtp
Classifier: Framework :: Pytest
Classifier: Operating System :: OS Independent
Classifier: Development Status :: 4 - Beta
Classifier: Intended Audience :: Developers
Classifier: License :: OSI Approved :: MIT License
Classifier: Programming Language :: Python :: 3
Classifier: Programming Language :: Python :: 3 :: Only
Classifier: Programming Language :: Python :: 3.6
Classifier: Programming Language :: Python :: 3.7
Classifier: Programming Language :: Python :: 3.8
Classifier: Programming Language :: Python :: 3.9
Classifier: Programming Language :: Python :: 3.10
Classifier: Programming Language :: Python :: 3.11
Classifier: Programming Language :: Python :: 3.12
Classifier: Programming Language :: Python :: 3.13
Classifier: Topic :: Software Development :: Testing
Requires-Python: >=3.6
License-File: LICENSE
License-File: AUTHORS
Requires-Dist: werkzeug >=0.10
Provides-Extra: smtp
Requires-Dist: aiosmtpd ; extra == 'smtp'
